tenantv1/__init__.py
tenantv1/client/__init__.py
tenantv1/client/tenant_api.py
tenantv1/client/tenant_client.py
tenantv1/middleware/__init__.py
tenantv1/middleware/middleware.py
tenantv1-1.0.7.dist-info/METADATA
tenantv1-1.0.7.dist-info/WHEEL
tenantv1-1.0.7.dist-info/top_level.txt
tenantv1-1.0.7.dist-info/RECORD
