Metadata-Version: 2.1
Name: tenantv1
Version: 1.0.7
Summary: project descriptions here
Home-page: https://github.com/FlyTOmeLight
Author: zhoubohan
Author-email: zhoubohan.pro@gmail.com
License: MIT
Classifier: Programming Language :: Python
Classifier: Programming Language :: Python :: 3
Classifier: Programming Language :: Python :: 3.7
Classifier: Programming Language :: Python :: 3.8
Classifier: Programming Language :: Python :: 3.9
Classifier: Programming Language :: Python :: 3.10
Requires-Python: >=3.7
Requires-Dist: fastapi
Requires-Dist: bce-internal-sdk
Requires-Dist: bceserver
Requires-Dist: bceidaas==0.0.1.dev2
Requires-Dist: bcelogger
